README.md
setup.cfg
setup.py
darkai/__init__.py
darkai.egg-info/PKG-INFO
darkai.egg-info/SOURCES.txt
darkai.egg-info/dependency_links.txt
darkai.egg-info/top_level.txt
darkai/observer/__init__.py
darkai/observer/accuracy_observer.py
darkai/observer/mean_squared_error_observer.py
darkai/observer/observer.py
darkai/optimizer/__init__.py
darkai/optimizer/gradient_descent.py
darkai/optimizer/optimizer.py
darkai/optimizer/gradient_descent_implementations/__init__.py
darkai/optimizer/gradient_descent_implementations/gradient_descent_perceptron.py
darkai/plugins/__init__.py
darkai/plugins/numpy_support.py
darkai/reinforcement/__init__.py
darkai/supervised/__init__.py
darkai/supervised/linear_regression.py
darkai/supervised/perceptron.py
darkai/supervised/supervised_model.py
darkai/types/__init__.py
darkai/unsupervised/__init__.py
darkai/unsupervised/unsupervised_model.py